LICENSE.gitignore
README.md
setup.cfg
setup.py
orchestra_logger/__init__.py
orchestra_logger.egg-info/PKG-INFO
orchestra_logger.egg-info/SOURCES.txt
orchestra_logger.egg-info/dependency_links.txt
orchestra_logger.egg-info/requires.txt
orchestra_logger.egg-info/top_level.txt
orchestra_logger/example/__init__.py
orchestra_logger/example/example.py
orchestra_logger/services/__init__.py
orchestra_logger/services/http/__init__.py
orchestra_logger/services/http/http.py
orchestra_logger/services/orcProcess/__init__.py
orchestra_logger/services/orcProcess/orcProcess.py
orchestra_logger/services/orchttp/__init__.py
orchestra_logger/services/orchttp/orchttp.py
orchestra_logger/services/system/__init__.py
orchestra_logger/services/system/system.py