Metadata-Version: 2.1
Name: orchestra-logger
Version: 0.0.12
Summary: Logging module to enable orchestration on self-hosted applications
Author: Orchestra (Hugo Lu)
Author-email: <hugo@getorchestra.io>
Keywords: python,logging,data,orchestration
Classifier: Development Status :: 3 - Alpha
Classifier: Intended Audience :: Developers
Classifier: Topic :: Software Development :: Build Tools
Classifier: License :: OSI Approved :: MIT License
Classifier: Programming Language :: Python :: 3.8
Classifier: Programming Language :: Python :: 3.9
License-File: LICENSE.gitignore
